ausData.py
ausData-0.0.4.dist-info/LICENSE.txt
ausData-0.0.4.dist-info/METADATA
ausData-0.0.4.dist-info/WHEEL
ausData-0.0.4.dist-info/top_level.txt
ausData-0.0.4.dist-info/RECORD
