Metadata-Version: 2.1
Name: ausData
Version: 0.0.4
Summary: Generate and validate Australian related data such as ABN, ACN, TFN.
Home-page: https://github.com/DucAnhD/ausData
Author: Jimmy Do
Author-email: ducanh0827@gmail.com
License: UNKNOWN
Platform: UNKNOWN
Classifier: Programming Language :: Python :: 3
Classifier: Programming Language :: Python :: 3.6
Classifier: Programming Language :: Python :: 3.8
Classifier: Programming Language :: Python :: 3.10
Classifier: Programming Language :: Python :: 3.9
Classifier: Programming Language :: Python :: 3.11
Classifier: Programming Language :: Python :: 3.12
Classifier: License :: Freely Distributable
